wbhuman_resources/__init__.py
wbhuman_resources/apps.py
wbhuman_resources/dynamic_preferences_registry.py
wbhuman_resources/tasks.py
wbhuman_resources/urls.py
wbhuman_resources/utils.py
wbhuman_resources/admin/__init__.py
wbhuman_resources/admin/absence.py
wbhuman_resources/admin/calendars.py
wbhuman_resources/admin/employee.py
wbhuman_resources/admin/kpi.py
wbhuman_resources/admin/review.py
wbhuman_resources/factories/__init__.py
wbhuman_resources/factories/absence.py
wbhuman_resources/factories/calendars.py
wbhuman_resources/factories/employee.py
wbhuman_resources/factories/kpi.py
wbhuman_resources/filters/__init__.py
wbhuman_resources/filters/absence.py
wbhuman_resources/filters/absence_graphs.py
wbhuman_resources/filters/calendars.py
wbhuman_resources/filters/employee.py
wbhuman_resources/filters/kpi.py
wbhuman_resources/filters/review.py
wbhuman_resources/filters/signals.py
wbhuman_resources/locale/de/LC_MESSAGES/django.po
wbhuman_resources/management/__init__.py
wbhuman_resources/migrations/0001_initial_squashed_squashed_0015_alter_absencerequest_calendaritem_ptr_and_more.py
wbhuman_resources/migrations/0016_alter_employeehumanresource_options.py
wbhuman_resources/migrations/0017_absencerequest_crossborder_country_and_more.py
wbhuman_resources/migrations/0018_remove_position_group_position_groups.py
wbhuman_resources/migrations/0019_alter_absencerequest_options_alter_kpi_options_and_more.py
wbhuman_resources/migrations/0020_alter_employeeyearbalance_year_alter_review_year.py
wbhuman_resources/migrations/0021_alter_position_color.py
wbhuman_resources/migrations/0022_remove_review_editable_mode.py
wbhuman_resources/migrations/__init__.py
wbhuman_resources/models/__init__.py
wbhuman_resources/models/absence.py
wbhuman_resources/models/calendars.py
wbhuman_resources/models/employee.py
wbhuman_resources/models/kpi.py
wbhuman_resources/models/preferences.py
wbhuman_resources/models/review.py
wbhuman_resources/permissions/__init__.py
wbhuman_resources-2.2.6.dist-info/METADATA
wbhuman_resources-2.2.6.dist-info/WHEEL
wbhuman_resources-2.2.6.dist-info/RECORD
