Metadata-Version: 2.4
Name: wbhuman_resources
Version: 2.2.6
Summary: A workbench module for managing human resources.
Author-email: Christopher Wittlinger <c.wittlinger@stainly.com>
Requires-Dist: wbcore
Requires-Dist: weasyprint==57.*
Requires-Dist: workalendar==17.*
Requires-Dist: xlsxwriter==3.*
